{"nodes": [{"id": "e_ashis_god_eyes_explorer_server_services_fetchers_mjs", "label": "fetchers.mjs", "file_type": "code", "source_file": "E:\\ashis\\god eyes\\explorer\\server\\services\\fetchers.mjs", "source_location": "L1"}, {"id": "fetchers_getopenskytoken", "label": "getOpenSkyToken()", "file_type": "code", "source_file": "E:\\ashis\\god eyes\\explorer\\server\\services\\fetchers.mjs", "source_location": "L32"}, {"id": "fetchers_fetchwithtimeout", "label": "fetchWithTimeout()", "file_type": "code", "source_file": "E:\\ashis\\god eyes\\explorer\\server\\services\\fetchers.mjs", "source_location": "L70"}, {"id": "fetchers_fetchopensky", "label": "fetchOpenSky()", "file_type": "code", "source_file": "E:\\ashis\\god eyes\\explorer\\server\\services\\fetchers.mjs", "source_location": "L87"}, {"id": "fetchers_fetchdarkfleet", "label": "fetchDarkFleet()", "file_type": "code", "source_file": "E:\\ashis\\god eyes\\explorer\\server\\services\\fetchers.mjs", "source_location": "L142"}], "edges": [{"source": "e_ashis_god_eyes_explorer_server_services_fetchers_mjs", "target": "e_ashis_god_eyes_explorer_server_config_constants_mjs", "relation": "imports_from", "confidence": "EXTRACTED", "source_file": "E:\\ashis\\god eyes\\explorer\\server\\services\\fetchers.mjs", "source_location": "L14", "weight": 1.0}, {"source": "e_ashis_god_eyes_explorer_server_services_fetchers_mjs", "target": "e_ashis_god_eyes_explorer_server_services_normalizer_mjs", "relation": "imports_from", "confidence": "EXTRACTED", "source_file": "E:\\ashis\\god eyes\\explorer\\server\\services\\fetchers.mjs", "source_location": "L21", "weight": 1.0}, {"source": "e_ashis_god_eyes_explorer_server_services_fetchers_mjs", "target": "e_ashis_god_eyes_explorer_server_store_flightcache_mjs", "relation": "imports_from", "confidence": "EXTRACTED", "source_file": "E:\\ashis\\god eyes\\explorer\\server\\services\\fetchers.mjs", "source_location": "L22", "weight": 1.0}, {"source": "e_ashis_god_eyes_explorer_server_services_fetchers_mjs", "target": "fetchers_getopenskytoken", "relation": "contains", "confidence": "EXTRACTED", "source_file": "E:\\ashis\\god eyes\\explorer\\server\\services\\fetchers.mjs", "source_location": "L32", "weight": 1.0}, {"source": "e_ashis_god_eyes_explorer_server_services_fetchers_mjs", "target": "fetchers_fetchwithtimeout", "relation": "contains", "confidence": "EXTRACTED", "source_file": "E:\\ashis\\god eyes\\explorer\\server\\services\\fetchers.mjs", "source_location": "L70", "weight": 1.0}, {"source": "e_ashis_god_eyes_explorer_server_services_fetchers_mjs", "target": "fetchers_fetchopensky", "relation": "contains", "confidence": "EXTRACTED", "source_file": "E:\\ashis\\god eyes\\explorer\\server\\services\\fetchers.mjs", "source_location": "L87", "weight": 1.0}, {"source": "e_ashis_god_eyes_explorer_server_services_fetchers_mjs", "target": "fetchers_fetchdarkfleet", "relation": "contains", "confidence": "EXTRACTED", "source_file": "E:\\ashis\\god eyes\\explorer\\server\\services\\fetchers.mjs", "source_location": "L142", "weight": 1.0}, {"source": "fetchers_getopenskytoken", "target": "fetchers_fetchwithtimeout", "relation": "calls", "confidence": "EXTRACTED", "source_file": "E:\\ashis\\god eyes\\explorer\\server\\services\\fetchers.mjs", "source_location": "L50", "weight": 1.0}, {"source": "fetchers_fetchopensky", "target": "fetchers_getopenskytoken", "relation": "calls", "confidence": "EXTRACTED", "source_file": "E:\\ashis\\god eyes\\explorer\\server\\services\\fetchers.mjs", "source_location": "L88", "weight": 1.0}, {"source": "fetchers_fetchopensky", "target": "fetchers_fetchwithtimeout", "relation": "calls", "confidence": "EXTRACTED", "source_file": "E:\\ashis\\god eyes\\explorer\\server\\services\\fetchers.mjs", "source_location": "L93", "weight": 1.0}, {"source": "fetchers_fetchdarkfleet", "target": "fetchers_fetchwithtimeout", "relation": "calls", "confidence": "EXTRACTED", "source_file": "E:\\ashis\\god eyes\\explorer\\server\\services\\fetchers.mjs", "source_location": "L147", "weight": 1.0}], "raw_calls": [{"caller_nid": "fetchers_getopenskytoken", "callee": "now", "source_file": "E:\\ashis\\god eyes\\explorer\\server\\services\\fetchers.mjs", "source_location": "L38"}, {"caller_nid": "fetchers_getopenskytoken", "callee": "json", "source_file": "E:\\ashis\\god eyes\\explorer\\server\\services\\fetchers.mjs", "source_location": "L58"}, {"caller_nid": "fetchers_getopenskytoken", "callee": "warn", "source_file": "E:\\ashis\\god eyes\\explorer\\server\\services\\fetchers.mjs", "source_location": "L64"}, {"caller_nid": "fetchers_fetchwithtimeout", "callee": "setTimeout", "source_file": "E:\\ashis\\god eyes\\explorer\\server\\services\\fetchers.mjs", "source_location": "L72"}, {"caller_nid": "fetchers_fetchwithtimeout", "callee": "finally", "source_file": "E:\\ashis\\god eyes\\explorer\\server\\services\\fetchers.mjs", "source_location": "L74"}, {"caller_nid": "fetchers_fetchwithtimeout", "callee": "fetch", "source_file": "E:\\ashis\\god eyes\\explorer\\server\\services\\fetchers.mjs", "source_location": "L74"}, {"caller_nid": "fetchers_fetchopensky", "callee": "json", "source_file": "E:\\ashis\\god eyes\\explorer\\server\\services\\fetchers.mjs", "source_location": "L108"}, {"caller_nid": "fetchers_fetchopensky", "callee": "isArray", "source_file": "E:\\ashis\\god eyes\\explorer\\server\\services\\fetchers.mjs", "source_location": "L111"}, {"caller_nid": "fetchers_fetchopensky", "callee": "normalizeOpenSky", "source_file": "E:\\ashis\\god eyes\\explorer\\server\\services\\fetchers.mjs", "source_location": "L117"}, {"caller_nid": "fetchers_fetchopensky", "callee": "upsertFlight", "source_file": "E:\\ashis\\god eyes\\explorer\\server\\services\\fetchers.mjs", "source_location": "L119"}, {"caller_nid": "fetchers_fetchopensky", "callee": "log", "source_file": "E:\\ashis\\god eyes\\explorer\\server\\services\\fetchers.mjs", "source_location": "L125"}, {"caller_nid": "fetchers_fetchdarkfleet", "callee": "json", "source_file": "E:\\ashis\\god eyes\\explorer\\server\\services\\fetchers.mjs", "source_location": "L153"}, {"caller_nid": "fetchers_fetchdarkfleet", "callee": "isArray", "source_file": "E:\\ashis\\god eyes\\explorer\\server\\services\\fetchers.mjs", "source_location": "L159"}, {"caller_nid": "fetchers_fetchdarkfleet", "callee": "floor", "source_file": "E:\\ashis\\god eyes\\explorer\\server\\services\\fetchers.mjs", "source_location": "L164"}, {"caller_nid": "fetchers_fetchdarkfleet", "callee": "now", "source_file": "E:\\ashis\\god eyes\\explorer\\server\\services\\fetchers.mjs", "source_location": "L164"}, {"caller_nid": "fetchers_fetchdarkfleet", "callee": "normalizeReadsb", "source_file": "E:\\ashis\\god eyes\\explorer\\server\\services\\fetchers.mjs", "source_location": "L171"}, {"caller_nid": "fetchers_fetchdarkfleet", "callee": "upsertFlight", "source_file": "E:\\ashis\\god eyes\\explorer\\server\\services\\fetchers.mjs", "source_location": "L173"}, {"caller_nid": "fetchers_fetchdarkfleet", "callee": "split", "source_file": "E:\\ashis\\god eyes\\explorer\\server\\services\\fetchers.mjs", "source_location": "L178"}, {"caller_nid": "fetchers_fetchdarkfleet", "callee": "log", "source_file": "E:\\ashis\\god eyes\\explorer\\server\\services\\fetchers.mjs", "source_location": "L179"}, {"caller_nid": "fetchers_fetchdarkfleet", "callee": "split", "source_file": "E:\\ashis\\god eyes\\explorer\\server\\services\\fetchers.mjs", "source_location": "L183"}, {"caller_nid": "fetchers_fetchdarkfleet", "callee": "warn", "source_file": "E:\\ashis\\god eyes\\explorer\\server\\services\\fetchers.mjs", "source_location": "L185"}]}